ProCap/__init__.py
procap-0.1.2.dist-info/METADATA
procap-0.1.2.dist-info/WHEEL
procap-0.1.2.dist-info/top_level.txt
procap-0.1.2.dist-info/RECORD
